cubicweb_processing/__init__.py
cubicweb_processing/__pkginfo__.py
cubicweb_processing/entities.py
cubicweb_processing/hooks.py
cubicweb_processing/schema.py
cubicweb_processing/testing.py
cubicweb_processing/workflows.py
cubicweb_processing/i18n/en.po
cubicweb_processing/i18n/fr.po
cubicweb_processing/migration/0.1.1_Any.py
cubicweb_processing/migration/0.2.1_Any.py
cubicweb_processing/migration/0.2.2_Any.py
cubicweb_processing/migration/0.2.3_Any.py
cubicweb_processing/migration/0.5.0_Any.py
cubicweb_processing/migration/0.6.0_Any.py
cubicweb_processing/migration/0.7.0_Any.py
cubicweb_processing/migration/0.8.0_Any.py
cubicweb_processing/migration/postcreate.py
cubicweb_processing/views/__init__.py
cubicweb_processing/views/actions.py
cubicweb_processing/views/controllers.py
cubicweb_processing/views/edition.py
cubicweb_processing/views/forms.py
cubicweb_processing/views/predicates.py
cubicweb_processing/views/primary.py
cubicweb_processing/views/uicfg.py
cubicweb_processing-0.14.0.dist-info/METADATA
cubicweb_processing-0.14.0.dist-info/WHEEL
cubicweb_processing-0.14.0.dist-info/entry_points.txt
cubicweb_processing-0.14.0.dist-info/top_level.txt
cubicweb_processing-0.14.0.dist-info/RECORD
